fastapi_mlflow/__init__.py
fastapi_mlflow/_mlflow_types.py
fastapi_mlflow/applications.py
fastapi_mlflow/exceptions.py
fastapi_mlflow/predictors.py
fastapi_mlflow-0.7.0.dist-info/LICENSE
fastapi_mlflow-0.7.0.dist-info/METADATA
fastapi_mlflow-0.7.0.dist-info/WHEEL
fastapi_mlflow-0.7.0.dist-info/RECORD
