Metadata-Version: 2.3
Name: fastapi-mlflow
Version: 0.7.0
Summary: Deploy mlflow models as JSON APIs with minimal new code.
License: Apache-2.0
Author: John Harrison
Author-email: john.harrison@autotrader.co.uk
Requires-Python: >=3.9
Classifier: License :: OSI Approved :: Apache Software License
Classifier: Programming Language :: Python :: 3
Classifier: Programming Language :: Python :: 3.9
Classifier: Programming Language :: Python :: 3.10
Classifier: Programming Language :: Python :: 3.11
Classifier: Programming Language :: Python :: 3.12
Classifier: Programming Language :: Python :: 3.13
Requires-Dist: fastapi (>=0.100.0,<1)
Requires-Dist: mlflow (>=2.0.1,<3.0.0)
Requires-Dist: numpy (>=1.22.1,<2.0.0)
Requires-Dist: orjson (>=3.9.5,<4.0.0)
Requires-Dist: pandas (<3)
Requires-Dist: pydantic (>=2.2.0,<3.0.0)
Project-URL: Repository, https://github.com/autotraderuk/fastapi-mlflow
